{
  "version": "1.3.0",
  "download_url": "https://raw.githubusercontent.com/martinkoudela-star/prommemories-configurator/main/prommemories-configurator.zip",
  "homepage": "https://github.com/martinkoudela-star/prommemories-configurator",
  "requires": "5.8",
  "tested": "6.6",
  "last_updated": "2026-07-04",
  "sections": {
    "description": "Konfigurátor cen služeb na maturitní plesy s administrací a shortcode [prommemories_configurator].",
    "changelog": "<h4>1.3.0</h4><ul><li>Nová karta \"Texty rozhraní\" v administraci — kompletně editovatelné všechny popisky, tlačítka a hlášky v konfigurátoru.</li></ul><h4>1.2.0</h4><ul><li>Na mobilu je cenová nabídka přichycená dole jako skládací lišta.</li></ul>"
  }
}
